vietcombank_captcha/__init__.py
vietcombank_captcha/cli.py
vietcombank_captcha/predictor.py
vietcombank_captcha/models/vietcombank_captcha.onnx
vietcombank_captcha-0.1.0.dist-info/METADATA
vietcombank_captcha-0.1.0.dist-info/WHEEL
vietcombank_captcha-0.1.0.dist-info/entry_points.txt
vietcombank_captcha-0.1.0.dist-info/licenses/LICENSE
vietcombank_captcha-0.1.0.dist-info/RECORD
