Metadata-Version: 2.4
Name: vietcombank-captcha
Version: 0.1.0
Summary: Lightweight CAPTCHA predictor for Vietcombank using ONNX
Project-URL: Homepage, https://github.com/bangprovn/vietcombank-captcha
Project-URL: Issues, https://github.com/bangprovn/vietcombank-captcha/issues
Author-email: bangprovn <me@bangprovn.com>
License: MIT
License-File: LICENSE
Keywords: captcha,machine-learning,ocr,onnx,vietcombank
Classifier: Development Status :: 4 - Beta
Classifier: Intended Audience :: Developers
Classifier: License :: OSI Approved :: MIT License
Classifier: Programming Language :: Python :: 3
Classifier: Programming Language :: Python :: 3.8
Classifier: Programming Language :: Python :: 3.9
Classifier: Programming Language :: Python :: 3.10
Classifier: Programming Language :: Python :: 3.11
Classifier: Programming Language :: Python :: 3.12
Classifier: Topic :: Scientific/Engineering :: Artificial Intelligence
Classifier: Topic :: Software Development :: Libraries :: Python Modules
Requires-Python: >=3.8
Requires-Dist: numpy<2.0.0,>=1.20.0
Requires-Dist: onnxruntime>=1.16.0
Requires-Dist: pillow>=9.0.0
Provides-Extra: dev
Requires-Dist: black>=23.0.0; extra == 'dev'
Requires-Dist: pytest>=7.0.0; extra == 'dev'
Requires-Dist: ruff>=0.1.0; extra == 'dev'
